ceader/__init__.py
ceader/__main__.py
ceader/adapters/__init__.py
ceader/adapters/file_disk_repo.py
ceader/app/__init__.py
ceader/domain/__init__.py
ceader/domain/repositories.py
ceader/domain/utils.py
ceader/domain/header_procedure/__init__.py
ceader/domain/header_procedure/add_header_procedure.py
ceader/domain/header_procedure/remove_header_procedure.py
ceader/domain/knowledge/__init__.py
ceader/domain/knowledge/extensions_to_language.py
ceader/domain/knowledge/language_to_comment.py
ceader/domain/types/__init__.py
ceader/domain/types/enums.py
ceader/ports/__init__.py
ceader/ports/cli.py
ceader/service/__init__.py
tests/component/__init__.py
tests/component/test_cli.py
tests/data/__init__.py
tests/data/fake_files/__init__.py
tests/data/fake_files/test_2.py
tests/integration/__init__.py
tests/integration/test_file_disk_repo.py
ceader-0.0.9.dist-info/LICENSE.txt
ceader-0.0.9.dist-info/METADATA
ceader-0.0.9.dist-info/WHEEL
ceader-0.0.9.dist-info/entry_points.txt
ceader-0.0.9.dist-info/top_level.txt
ceader-0.0.9.dist-info/RECORD
