Metadata-Version: 2.1
Name: ceader
Version: 0.0.9
Summary: Tool for automatically adding a header to files in the form of a comment.
Home-page: https://github.com/cerebre-io/ceader
Author: Kamil Jankowski
Author-email: mr.kamil.jankowski@gmail.com
License: MIT
Keywords: Header
Platform: UNKNOWN
Classifier: Programming Language :: Python :: 3
License-File: LICENSE.txt
